LICENCE.md
README.md
pyproject.toml
setup.py
scrapeops_python_logger/__init__.py
scrapeops_python_logger/exceptions.py
scrapeops_python_logger/scrapeops_logger.py
scrapeops_python_logger.egg-info/PKG-INFO
scrapeops_python_logger.egg-info/SOURCES.txt
scrapeops_python_logger.egg-info/dependency_links.txt
scrapeops_python_logger.egg-info/requires.txt
scrapeops_python_logger.egg-info/top_level.txt
scrapeops_python_logger/core/__init__.py
scrapeops_python_logger/core/api.py
scrapeops_python_logger/core/controllers.py
scrapeops_python_logger/core/error_logger.py
scrapeops_python_logger/core/model.py
scrapeops_python_logger/core/setup.py
scrapeops_python_logger/normalizer/__init__.py
scrapeops_python_logger/normalizer/domains.py
scrapeops_python_logger/normalizer/exceptions.py
scrapeops_python_logger/normalizer/middleware.py
scrapeops_python_logger/normalizer/proxies.py
scrapeops_python_logger/normalizer/proxy_port_normalizer.py
scrapeops_python_logger/normalizer/request_response.py
scrapeops_python_logger/stats/__init__.py
scrapeops_python_logger/stats/logger.py
scrapeops_python_logger/stats/model.py
scrapeops_python_logger/utils/__init__.py
scrapeops_python_logger/utils/error_handling.py
scrapeops_python_logger/utils/utils.py
scrapeops_python_logger/validators/__init__.py
scrapeops_python_logger/validators/item_validator.py
scrapeops_python_logger/validators/response_validator.py